CHANGES.rst
CONTRIBUTORS.rst
MANIFEST.in
README.rst
setup.cfg
setup.py
docs/LICENSE.GPL
docs/LICENSE.txt
src/sc/__init__.py
src/sc.microsite.egg-info/PKG-INFO
src/sc.microsite.egg-info/SOURCES.txt
src/sc.microsite.egg-info/dependency_links.txt
src/sc.microsite.egg-info/entry_points.txt
src/sc.microsite.egg-info/namespace_packages.txt
src/sc.microsite.egg-info/not-zip-safe
src/sc.microsite.egg-info/requires.txt
src/sc.microsite.egg-info/top_level.txt
src/sc/microsite/__init__.py
src/sc/microsite/config.py
src/sc/microsite/configure.zcml
src/sc/microsite/content.py
src/sc/microsite/interfaces.py
src/sc/microsite/logger.py
src/sc/microsite/profiles.zcml
src/sc/microsite/testing.py
src/sc/microsite/locales/manual.pot
src/sc/microsite/locales/plone.pot
src/sc/microsite/locales/sc.microsite.pot
src/sc/microsite/locales/es/LC_MESSAGES/plone.po
src/sc/microsite/locales/es/LC_MESSAGES/sc.microsite.po
src/sc/microsite/locales/pt_BR/LC_MESSAGES/plone.po
src/sc/microsite/locales/pt_BR/LC_MESSAGES/sc.microsite.po
src/sc/microsite/profiles/default/metadata.xml
src/sc/microsite/profiles/default/rolemap.xml
src/sc/microsite/profiles/default/types.xml
src/sc/microsite/profiles/default/types/sc.microsite.xml
src/sc/microsite/profiles/uninstall/sc.microsite.txt
src/sc/microsite/static/1376611926_appicns_folder_site.png
src/sc/microsite/static/microsite_icon.png
src/sc/microsite/subscribers/__init__.py
src/sc/microsite/subscribers/configure.zcml
src/sc/microsite/subscribers/microsite.py
src/sc/microsite/tests/__init__.py
src/sc/microsite/tests/test_microsite.py
src/sc/microsite/tests/test_setup.py
src/sc/microsite/tests/test_upgrades.py
src/sc/microsite/upgrades/__init__.py
src/sc/microsite/upgrades/configure.zcml
src/sc/microsite/upgrades/v1000/__init__.py
src/sc/microsite/upgrades/v1000/configure.zcml
src/sc/microsite/upgrades/v1000/handler.py
src/sc/microsite/upgrades/v1001/__init__.py
src/sc/microsite/upgrades/v1001/configure.zcml
src/sc/microsite/upgrades/v1001/handler.py
src/sc/microsite/upgrades/v1001/profile/rolemap.xml
src/sc/microsite/upgrades/v1001/profile/types/sc.microsite.xml