Metadata-Version: 1.1
Name: sc.microsite
Version: 1.1b1
Summary: ('A very basic Dexterity-based container to be used as a microsite.',)
Home-page: https://github.com/simplesconsultoria/sc.microsite
Author: Simples Consultoria
Author-email: products@simplesconsultoria.com.br
License: UNKNOWN
Keywords: plone microsite dexterity hotsite
Platform: UNKNOWN
Classifier: Development Status :: 4 - Beta
Classifier: Environment :: Web Environment
Classifier: Framework :: Plone
Classifier: Framework :: Plone :: 4.3
Classifier: Intended Audience :: End Users/Desktop
Classifier: Intended Audience :: System Administrators
Classifier: License :: OSI Approved :: GNU General Public License v2 (GPLv2)
Classifier: Operating System :: OS Independent
Classifier: Programming Language :: JavaScript
Classifier: Programming Language :: Python
Classifier: Programming Language :: Python :: 2.7
Classifier: Topic :: Office/Business :: News/Diary
Classifier: Topic :: Software Development :: Libraries :: Python Modules
